siapy-0.9.7.dist-info/METADATA
siapy-0.9.7.dist-info/WHEEL
siapy-0.9.7.dist-info/entry_points.txt
siapy-0.9.7.dist-info/licenses/LICENSE
siapy/__init__.py
siapy/__version__.py
siapy/core/__init__.py
siapy/core/configs.py
siapy/core/exceptions.py
siapy/core/logger.py
siapy/core/types.py
siapy/datasets/__init__.py
siapy/datasets/helpers.py
siapy/datasets/schemas.py
siapy/datasets/tabular.py
siapy/entities/__init__.py
siapy/entities/images/__init__.py
siapy/entities/images/interfaces.py
siapy/entities/images/mock.py
siapy/entities/images/rasterio_lib.py
siapy/entities/images/spectral_lib.py
siapy/entities/images/spimage.py
siapy/entities/imagesets.py
siapy/entities/pixels.py
siapy/entities/shapes/__init__.py
siapy/entities/shapes/geometric_shapes.py
siapy/entities/shapes/shape.py
siapy/entities/signatures.py
siapy/features/__init__.py
siapy/features/features.py
siapy/features/helpers.py
siapy/features/spectral_indices.py
siapy/optimizers/__init__.py
siapy/optimizers/configs.py
siapy/optimizers/evaluators.py
siapy/optimizers/metrics.py
siapy/optimizers/optimizers.py
siapy/optimizers/parameters.py
siapy/optimizers/scorers.py
siapy/py.typed
siapy/transformations/__init__.py
siapy/transformations/corregistrator.py
siapy/transformations/image.py
siapy/utils/__init__.py
siapy/utils/general.py
siapy/utils/image_validators.py
siapy/utils/images.py
siapy/utils/plots.py
siapy/utils/signatures.py
siapy-0.9.7.dist-info/RECORD
