Metadata-Version: 2.1
Name: siapy
Version: 0.9.7
Summary: A python library for efficient processing of spectral images.
Author-Email: janezlapajne <janez.lapajne@kis.si>
License: MIT
Classifier: Intended Audience :: Information Technology
Classifier: Operating System :: OS Independent
Classifier: Programming Language :: Python :: 3
Classifier: Programming Language :: Python
Classifier: Topic :: Internet
Classifier: Topic :: Software Development :: Libraries :: Python Modules
Classifier: Topic :: Software Development :: Libraries
Classifier: Topic :: Software Development
Classifier: Typing :: Typed
Classifier: Intended Audience :: Developers
Classifier: License :: OSI Approved :: MIT License
Classifier: Programming Language :: Python :: 3 :: Only
Classifier: Programming Language :: Python :: 3.10
Classifier: Programming Language :: Python :: 3.11
Classifier: Programming Language :: Python :: 3.12
Project-URL: Homepage, https://github.com/siapy/siapy-lib
Project-URL: Documentation, https://github.com/siapy/siapy-lib/tree/main/docs
Project-URL: Repository, https://github.com/siapy/siapy-lib
Requires-Python: <3.13,>=3.10
Requires-Dist: pandas>=2.2.2
Requires-Dist: opencv-python>=4.10.0.82
Requires-Dist: spectral>=0.23.1
Requires-Dist: scikit-learn>=1.5.0
Requires-Dist: pydantic>=2.7.3
Requires-Dist: rich>=13.7.1
Requires-Dist: scikit-image>=0.24.0
Requires-Dist: matplotlib>=3.9.0
Requires-Dist: optuna>=3.6.1
Requires-Dist: spyndex>=0.6.0
Requires-Dist: mlxtend>=0.23.1
Requires-Dist: autofeat>=2.1.1
Requires-Dist: setuptools>=72.1.0
Requires-Dist: dask[dataframe]>=2024.7.1
Requires-Dist: geopandas>=1.0.1
Requires-Dist: rasterio>=1.4.3
Requires-Dist: xarray>=2025.1.2
Requires-Dist: rioxarray>=0.18.2
Requires-Dist: shapely>=2.0.7
